torn_open/__init__.py
torn_open/annotated_handler.py
torn_open/handlers.py
torn_open/models.py
torn_open/types.py
torn_open/web.py
torn_open/api_spec/__init__.py
torn_open/api_spec/core.py
torn_open/api_spec/create_api_spec.py
torn_open/api_spec/decorators.py
torn_open/api_spec/exception_finder.py
torn_open/api_spec/plugin.py
torn_open-0.0.3.dist-info/METADATA
torn_open-0.0.3.dist-info/WHEEL
torn_open-0.0.3.dist-info/top_level.txt
torn_open-0.0.3.dist-info/RECORD
