Metadata-Version: 2.1
Name: torn-open
Version: 0.0.3
Summary: Tornado x OpenAPI x Redoc
Home-page: https://github.com/b34nst4lk/tornopen/
Author: Jack Sim
License: MIT
Platform: UNKNOWN
Requires-Python: >=3.6.*
Requires-Dist: apispec
Requires-Dist: pydantic
Requires-Dist: tornado
Requires-Dist: typed-ast ; python_version >= "3.8"
